django_graphql_app_setup/__init__.py
django_graphql_app_setup/apps.py
django_graphql_app_setup/management/__init__.py
django_graphql_app_setup/management/commands/__init__.py
django_graphql_app_setup/management/commands/startgqlapp.py
django_graphql_app_setup-0.2.4.dist-info/LICENSE
django_graphql_app_setup-0.2.4.dist-info/METADATA
django_graphql_app_setup-0.2.4.dist-info/WHEEL
django_graphql_app_setup-0.2.4.dist-info/top_level.txt
django_graphql_app_setup-0.2.4.dist-info/RECORD
