Metadata-Version: 2.2
Name: django-graphql-app-setup
Version: 0.2.4
Summary: A Django management command to create apps with custom folder structures for graphql APIs.
Home-page: https://github.com/paisoncodes/django-graphql-app-setup
Author: Olatunji Komolafe
Author-email: iamokomolafe.o.s@gmail.com
Classifier: Development Status :: 3 - Alpha
Classifier: Intended Audience :: Developers
Classifier: License :: OSI Approved :: MIT License
Classifier: Programming Language :: Python :: 3
Classifier: Programming Language :: Python :: 3.7
Classifier: Programming Language :: Python :: 3.8
Classifier: Programming Language :: Python :: 3.9
Classifier: Programming Language :: Python :: 3.10
Classifier: Framework :: Django
Classifier: Framework :: Django :: 3.0
Classifier: Framework :: Django :: 3.1
Classifier: Framework :: Django :: 3.2
Classifier: Framework :: Django :: 4.0
Requires-Python: >=3.7
License-File: LICENSE
Requires-Dist: Django>=3.0
Requires-Dist: graphene>=3.0
Dynamic: author
Dynamic: author-email
Dynamic: classifier
Dynamic: description
Dynamic: description-content-type
Dynamic: home-page
Dynamic: requires-dist
Dynamic: requires-python
Dynamic: summary
